{
    "configurations": [
        {
            "name": "Win32",
            "includePath": [
                "${workspaceFolder}/**"
            ],
            "defines": [
                "_DEBUG",
                "UNICODE",
                "_UNICODE"
            ],
            "compilerPath": "cl.exe",
            "intelliSenseMode": "windows-msvc-x64"
        },
        {
            "name": "kbhit",
            "includePath": [
                "${workspaceFolder}/**"
            ],
            "defines": [
                "_DEBUG",
                "UNICODE",
                "_UNICODE"
            ],
            "compilerPath": "C:/MinGW/bin/cpp.exe",
            "intelliSenseMode": "windows-gcc-x64"
        }
    ],
    "version": 4
}